odoo10_addon_shopinvader_sale_report-10.0.1.0.1-nspkg.pth
odoo/addons/shopinvader_sale_report/__init__.py
odoo/addons/shopinvader_sale_report/__manifest__.py
odoo/addons/shopinvader_sale_report/reports/__init__.py
odoo/addons/shopinvader_sale_report/reports/sale_report.py
odoo10_addon_shopinvader_sale_report-10.0.1.0.1.dist-info/METADATA
odoo10_addon_shopinvader_sale_report-10.0.1.0.1.dist-info/WHEEL
odoo10_addon_shopinvader_sale_report-10.0.1.0.1.dist-info/namespace_packages.txt
odoo10_addon_shopinvader_sale_report-10.0.1.0.1.dist-info/top_level.txt
odoo10_addon_shopinvader_sale_report-10.0.1.0.1.dist-info/RECORD
